flet_easy/__init__.py
flet_easy/auto_route.py
flet_easy/datasy.py
flet_easy/exceptions.py
flet_easy/extra.py
flet_easy/extrasJwt.py
flet_easy/fletEasy.py
flet_easy/inheritance.py
flet_easy/job.py
flet_easy/jwt.py
flet_easy/pagesy.py
flet_easy/route.py
flet_easy/view_404.py
flet_easy/cli/main.py
flet_easy-0.2.9.dist-info/METADATA
flet_easy-0.2.9.dist-info/WHEEL
flet_easy-0.2.9.dist-info/entry_points.txt
flet_easy-0.2.9.dist-info/licenses/LICENSE
flet_easy-0.2.9.dist-info/RECORD
