Metadata-Version: 2.4
Name: flet-easy
Version: 0.2.9
Summary: ⚡Flet-Easy is a user-friendly add-on package for Flet, offering a cleaner code structure with numerous customizable features like JWT, routers, decorators, middleware and more.
Project-URL: Homepage, https://github.com/Daxexs
Project-URL: Repository, https://github.com/Daxexs/flet-easy
Project-URL: Documentation, https://daxexs.github.io/flet-easy
Project-URL: Changelog, https://github.com/Daxexs/flet-easy/blob/main/CHANGELOG.md
Author-email: Daxexs <Daxexsdev@gmail.com>
License: apache-2.0
License-File: LICENSE
Keywords: app python,fast flet,flet,flet easy,flet easy fastapi,flet easy mvc,flet easy route,flet jwt,flet middleware,flet mvc,flet route,flutter python,python,python web template,web application
Classifier: Programming Language :: Python :: 3
Classifier: Programming Language :: Python :: 3.8
Classifier: Programming Language :: Python :: 3.9
Classifier: Programming Language :: Python :: 3.10
Classifier: Programming Language :: Python :: 3.11
Classifier: Programming Language :: Python :: 3.12
Classifier: Topic :: Software Development :: Build Tools
Requires-Python: >=3.8
Provides-Extra: all
Requires-Dist: cookiecutter>=2.6.0; extra == 'all'
Requires-Dist: flet[all]>=0.25.1; extra == 'all'
Requires-Dist: pyjwt>=2.0.0; extra == 'all'
Requires-Dist: rich-argparse>=1.4.0; extra == 'all'
Requires-Dist: rsa>=4.9; extra == 'all'
Provides-Extra: cli
Requires-Dist: cookiecutter>=2.6.0; extra == 'cli'
Requires-Dist: flet[all]>=0.25.1; extra == 'cli'
Requires-Dist: rich-argparse>=1.4.0; extra == 'cli'
Provides-Extra: jwt
Requires-Dist: pyjwt>=2.0.0; extra == 'jwt'
Requires-Dist: rsa>=4.9; extra == 'jwt'
